hrms_connect/main.py
hrms_connect/services/check_in.py
hrms_connect/services/check_out.py
hrms_connect/services/login.py
hrms_connect/services/logout.py
hrms_connect/services/project_service.py
hrms_connect/services/report.py
hrms_connect-1.0.4.dist-info/METADATA
hrms_connect-1.0.4.dist-info/WHEEL
hrms_connect-1.0.4.dist-info/entry_points.txt
hrms_connect-1.0.4.dist-info/top_level.txt
hrms_connect-1.0.4.dist-info/RECORD
